Metadata-Version: 2.1
Name: meu_investimento_lib_arraes
Version: 0.1
Summary: Uma biblioteca para cálculos de investimentos.
Home-page: https://github.com/parraes/postech
Author: Pedro Arraes
Author-email: pedroarraes@gmail.com
Classifier: Programming Language :: Python :: 3
Classifier: License :: OSI Approved :: MIT License
Classifier: Operating System :: OS Independent
Requires-Python: >=3.6
